LICENSE
MANIFEST.in
README
README.md
setup.py
rosbag_metadata/__init__.py
rosbag_metadata/config.py
rosbag_metadata/metadata_writer.py
rosbag_metadata/rosbag_metadata.py
rosbag_metadata/system_info_collector.py
rosbag_metadata/utils.py
rosbag_metadata.egg-info/PKG-INFO
rosbag_metadata.egg-info/SOURCES.txt
rosbag_metadata.egg-info/dependency_links.txt
rosbag_metadata.egg-info/entry_points.txt
rosbag_metadata.egg-info/requires.txt
rosbag_metadata.egg-info/top_level.txt