Metadata-Version: 1.1
Name: rosbag-metadata
Version: 0.1.6
Summary: Tool for collecting and writing metadata to ROS bagfiles or to accompanying yaml files.
Home-page: http://rosbag-metadata.readthedocs.org/
Author: Hordur K Heidarsson
Author-email: hordur@hordur.us
License: MIT
Keywords: ros rosbag metadata
Platform: UNKNOWN
Classifier: Development Status :: 3 - Alpha
Classifier: Topic :: Utilities
Classifier: License :: OSI Approved :: MIT License
